Metadata-Version: 2.1
Name: gameturtle
Version: 0.24
Summary: Python gameturtle Module for make animations and games easily，by www.lixingqiu.com 
Home-page: http://www.lixingqiu.com
Author: lixingqiu
Author-email: 406273900@qq.com
License: MIT
Keywords: turtle game tkinter game pillow numpy pixel collide
Platform: UNKNOWN
